{
    "default" : {
        "security": {
            "apiKeys": {
                "9579d2bc-6dc0-4be6-80c4-44d95be205f9": "Greg Miller"
            }
        },
        "database": {
            "parse": {
                "dashboard" : {
                    "users" : [
                        {
                            "user" : "ADD USER NAME TO ACCESS DASHBOARD",
                            "pass" : "ADD PASSWORD"
                        }
                    ]
                }
            }
        },
        "services": {
            "exampleService": {
                "apiKey": "PRE PROD API KEY"
            }
        }
    },
    "development" : {
        "database": {
            "parse": {
                "server" : {
                    "databaseURL": "Your DEV Mongo DB Connection URL here",
                    "masterKey": "MAKE UP A MASTER KEY",
                    "appId" : "MAKE UP AN APP ID"
                }
            }
        }
    },
    "production" : {
        "database": {
            "parse": {
                "server" : {
                    "databaseURL": "Your PROD Mongo DB Connection URL here",
                    "masterKey": "Make up a master Key",
                    "appId" : "MAKE UP AN APP ID"
                }
            }
        },
        "services": {
            "exampleService": {
                "apiKey": "PROD API KEY"
            }
        }
    }
}